sphinx_vhs/__init__.py
sphinx_vhs/_version.py
sphinx_vhs/py.typed
sphinx_vhs-1.5.1.dist-info/licenses/LICENSE
sphinx_vhs-1.5.1.dist-info/METADATA
sphinx_vhs-1.5.1.dist-info/WHEEL
sphinx_vhs-1.5.1.dist-info/top_level.txt
sphinx_vhs-1.5.1.dist-info/RECORD
