Metadata-Version: 2.4
Name: sphinx-vhs
Version: 1.5.1
Summary: Sphinx plugin that generates terminal GIFs using charm's VHS
Author-email: Tamika Nomara <taminomara@gmail.com>
License-Expression: MIT
Project-URL: Documentation, https://sphinx-vhs.readthedocs.io/en/stable/
Project-URL: Issues, https://github.com/sphinx-contrib/vhs/issues/
Project-URL: Source, https://github.com/sphinx-contrib/vhs/
Project-URL: Changelog, https://github.com/sphinx-contrib/vhs/blob/main/CHANGELOG.md
Classifier: Development Status :: 5 - Production/Stable
Classifier: Programming Language :: Python :: 3
Classifier: Programming Language :: Python :: 3 :: Only
Classifier: Programming Language :: Python :: 3.11
Classifier: Programming Language :: Python :: 3.12
Classifier: Programming Language :: Python :: 3.13
Classifier: Framework :: Sphinx
Classifier: Framework :: Sphinx :: Extension
Classifier: Topic :: Software Development :: Documentation
Classifier: Topic :: Documentation
Classifier: Topic :: Documentation :: Sphinx
Classifier: Intended Audience :: Developers
Classifier: Typing :: Typed
Requires-Python: >=3.11
License-File: LICENSE
Requires-Dist: sphinx<10.0,>=8.0
Requires-Dist: vhs<2.0,>=1.1.0
Dynamic: license-file
